setup.py
QtArgSelector.egg-info/PKG-INFO
QtArgSelector.egg-info/SOURCES.txt
QtArgSelector.egg-info/dependency_links.txt
QtArgSelector.egg-info/requires.txt
QtArgSelector.egg-info/top_level.txt
qtargs/QtArgSelector.py
qtargs/__init__.py