Metadata-Version: 1.1
Name: QtArgSelector
Version: 1.0.0
Summary: Select program arguments with GUI
Home-page: https://github.com/drilldripper/QtArgSelector
Author: drilldripper
Author-email: ryo.kt.in@gmail.com
License: MIT
Keywords: PyQt argument
Platform: POSIX
Platform: Windows
Platform: Mac OS
Classifier: Intended Audience :: Developers
Classifier: Operating System :: OS Independent
Classifier: Programming Language :: Python
Classifier: Topic :: Utilities
Classifier: License :: OSI Approved :: MIT License
